calamine_tablib-0.1.4.dist-info/METADATA
calamine_tablib-0.1.4.dist-info/WHEEL
calamine_tablib/monkeypatches.py
calamine_tablib/__init__.py
calamine_tablib/py.typed
calamine_tablib/format.py
calamine_tablib/_calamine_tablib.pyi
calamine_tablib/_calamine_tablib.cpython-311-x86_64-linux-gnu.so
calamine_tablib-0.1.4.dist-info/RECORD
