Metadata-Version: 2.1
Name: calamine-tablib
Version: 0.1.4
Classifier: Programming Language :: Rust
Classifier: Programming Language :: Python :: Implementation :: CPython
Classifier: Programming Language :: Python :: Implementation :: PyPy
Requires-Dist: tablib >=3.5, <4.0
Requires-Dist: PyExcelerate >=0.10, <1.0
Requires-Python: >=3.8
